{"type":"FeatureCollection","features":[{"type":"Feature","properties":{"nome":"Ponta da Pita","osm_id":6641014385,"osm_tipo":"node","tipo_lugar":"neighbourhood"},"geometry":{"type":"Point","coordinates":[-48.6858239,-25.4535602]}},{"type":"Feature","properties":{"nome":"Batel","osm_id":8727754992,"osm_tipo":"node","tipo_lugar":"neighbourhood"},"geometry":{"type":"Point","coordinates":[-48.7247085,-25.4331254]}},{"type":"Feature","properties":{"nome":"Laranjeiras","osm_id":8727754993,"osm_tipo":"node","tipo_lugar":"neighbourhood"},"geometry":{"type":"Point","coordinates":[-48.7130103,-25.4268219]}},{"type":"Feature","properties":{"nome":"Tucunduva","osm_id":8817974776,"osm_tipo":"node","tipo_lugar":"neighbourhood"},"geometry":{"type":"Point","coordinates":[-48.7264788,-25.4268683]}},{"type":"Feature","properties":{"nome":"Malvinas","osm_id":8817974777,"osm_tipo":"node","tipo_lugar":"neighbourhood"},"geometry":{"type":"Point","coordinates":[-48.7288367,-25.4319351]}},{"type":"Feature","properties":{"nome":"Centro Histórico","osm_id":8817974778,"osm_tipo":"node","tipo_lugar":"neighbourhood"},"geometry":{"type":"Point","coordinates":[-48.7119372,-25.430311]}},{"type":"Feature","properties":{"nome":"Penha","osm_id":8817974779,"osm_tipo":"node","tipo_lugar":"neighbourhood"},"geometry":{"type":"Point","coordinates":[-48.7088834,-25.438338]}},{"type":"Feature","properties":{"nome":"Jardim Maria Luiza","osm_id":8817974780,"osm_tipo":"node","tipo_lugar":"neighbourhood"},"geometry":{"type":"Point","coordinates":[-48.7147539,-25.4351513]}},{"type":"Feature","properties":{"nome":"Caixa d´Água","osm_id":8817974781,"osm_tipo":"node","tipo_lugar":"neighbourhood"},"geometry":{"type":"Point","coordinates":[-48.7184779,-25.434182]}},{"type":"Feature","properties":{"nome":"Guapê","osm_id":9768975341,"osm_tipo":"node","tipo_lugar":"neighbourhood"},"geometry":{"type":"Point","coordinates":[-48.735932,-25.4348936]}},{"type":"Feature","properties":{"nome":"Graciosa","osm_id":10123665835,"osm_tipo":"node","tipo_lugar":"neighbourhood"},"geometry":{"type":"Point","coordinates":[-48.7156711,-25.4203849]}},{"type":"Feature","properties":{"nome":"Jardim Barigui","osm_id":10132873135,"osm_tipo":"node","tipo_lugar":"neighbourhood"},"geometry":{"type":"Point","coordinates":[-48.7410114,-25.4333598]}},{"type":"Feature","properties":{"nome":"Itapema","osm_id":10184771706,"osm_tipo":"node","tipo_lugar":"neighbourhood"},"geometry":{"type":"Point","coordinates":[-48.6901098,-25.4565023]}},{"type":"Feature","properties":{"nome":"Pinheirinho","osm_id":10184771716,"osm_tipo":"node","tipo_lugar":"neighbourhood"},"geometry":{"type":"Point","coordinates":[-48.686698,-25.4676905]}},{"type":"Feature","properties":{"nome":"Praia dos Polacos","osm_id":10187083595,"osm_tipo":"node","tipo_lugar":"neighbourhood"},"geometry":{"type":"Point","coordinates":[-48.6907285,-25.451054]}},{"type":"Feature","properties":{"nome":"KM 4","osm_id":10266450465,"osm_tipo":"node","tipo_lugar":"neighbourhood"},"geometry":{"type":"Point","coordinates":[-48.7533085,-25.4376013]}},{"type":"Feature","properties":{"nome":"Saivá","osm_id":10266450466,"osm_tipo":"node","tipo_lugar":"neighbourhood"},"geometry":{"type":"Point","coordinates":[-48.7276011,-25.4376719]}},{"type":"Feature","properties":{"nome":"Residencial Itapema","osm_id":10266450467,"osm_tipo":"node","tipo_lugar":"neighbourhood"},"geometry":{"type":"Point","coordinates":[-48.7133542,-25.4378994]}},{"type":"Feature","properties":{"nome":"Gamboa","osm_id":10266450468,"osm_tipo":"node","tipo_lugar":"neighbourhood"},"geometry":{"type":"Point","coordinates":[-48.6999194,-25.4479858]}},{"type":"Feature","properties":{"nome":"Graciosa","osm_id":10266450485,"osm_tipo":"node","tipo_lugar":"neighbourhood"},"geometry":{"type":"Point","coordinates":[-48.7112502,-25.4242739]}},{"type":"Feature","properties":{"nome":"Cabral","osm_id":11563877069,"osm_tipo":"node","tipo_lugar":"neighbourhood"},"geometry":{"type":"Point","coordinates":[-48.7186911,-25.4170057]}}]}