{"type":"FeatureCollection","features":[{"type":"Feature","properties":{"nome":"Moinho Velho","osm_id":4821713390,"osm_tipo":"node","tipo_lugar":"suburb"},"geometry":{"type":"Point","coordinates":[-51.1041305,-29.5898755]}},{"type":"Feature","properties":{"nome":"São Miguel","osm_id":4821713391,"osm_tipo":"node","tipo_lugar":"suburb"},"geometry":{"type":"Point","coordinates":[-51.1184629,-29.5854345]}},{"type":"Feature","properties":{"nome":"Floresta","osm_id":5312991112,"osm_tipo":"node","tipo_lugar":"suburb"},"geometry":{"type":"Point","coordinates":[-51.0903326,-29.5766805]}},{"type":"Feature","properties":{"nome":"União","osm_id":5312991113,"osm_tipo":"node","tipo_lugar":"suburb"},"geometry":{"type":"Point","coordinates":[-51.0825121,-29.5743576]}},{"type":"Feature","properties":{"nome":"Centro","osm_id":5312991114,"osm_tipo":"node","tipo_lugar":"suburb"},"geometry":{"type":"Point","coordinates":[-51.0881164,-29.5859239]}},{"type":"Feature","properties":{"nome":"Industrial","osm_id":5312991115,"osm_tipo":"node","tipo_lugar":"suburb"},"geometry":{"type":"Point","coordinates":[-51.0817436,-29.5888902]}},{"type":"Feature","properties":{"nome":"Vale Verde","osm_id":5312991116,"osm_tipo":"node","tipo_lugar":"suburb"},"geometry":{"type":"Point","coordinates":[-51.0919466,-29.5693734]}},{"type":"Feature","properties":{"nome":"São Pedro","osm_id":5312991117,"osm_tipo":"node","tipo_lugar":"suburb"},"geometry":{"type":"Point","coordinates":[-51.0808406,-29.5937258]}},{"type":"Feature","properties":{"nome":"Portal da Serra","osm_id":5312991118,"osm_tipo":"node","tipo_lugar":"suburb"},"geometry":{"type":"Point","coordinates":[-51.0999993,-29.5837154]}},{"type":"Feature","properties":{"nome":"Sete de Setembro","osm_id":5312991119,"osm_tipo":"node","tipo_lugar":"suburb"},"geometry":{"type":"Point","coordinates":[-51.0799496,-29.582156]}},{"type":"Feature","properties":{"nome":"Becker","osm_id":5312991120,"osm_tipo":"node","tipo_lugar":"suburb"},"geometry":{"type":"Point","coordinates":[-51.0706656,-29.5946838]}},{"type":"Feature","properties":{"nome":"Vila Rosa","osm_id":5312991121,"osm_tipo":"node","tipo_lugar":"suburb"},"geometry":{"type":"Point","coordinates":[-51.0951237,-29.6006678]}},{"type":"Feature","properties":{"nome":"Beira Rio","osm_id":5312991122,"osm_tipo":"node","tipo_lugar":"suburb"},"geometry":{"type":"Point","coordinates":[-51.0938443,-29.5941926]}},{"type":"Feature","properties":{"nome":"Primavera","osm_id":5312991123,"osm_tipo":"node","tipo_lugar":"suburb"},"geometry":{"type":"Point","coordinates":[-51.0951907,-29.5856095]}},{"type":"Feature","properties":{"nome":"São João","osm_id":5312991124,"osm_tipo":"node","tipo_lugar":"suburb"},"geometry":{"type":"Point","coordinates":[-51.080771,-29.5996996]}},{"type":"Feature","properties":{"nome":"Navegantes","osm_id":8729025351,"osm_tipo":"node","tipo_lugar":"suburb"},"geometry":{"type":"Point","coordinates":[-51.0734795,-29.587431]}},{"type":"Feature","properties":{"nome":"Bela Vista","osm_id":8901120963,"osm_tipo":"node","tipo_lugar":"suburb"},"geometry":{"type":"Point","coordinates":[-51.1021543,-29.57831]}},{"type":"Feature","properties":{"nome":"Travessão","osm_id":8901133229,"osm_tipo":"node","tipo_lugar":"suburb"},"geometry":{"type":"Point","coordinates":[-51.1183498,-29.6224658]}},{"type":"Feature","properties":{"nome":"Vale Direito","osm_id":8901151497,"osm_tipo":"node","tipo_lugar":"suburb"},"geometry":{"type":"Point","coordinates":[-51.0806721,-29.5668161]}},{"type":"Feature","properties":{"nome":"Vale Esquerdo","osm_id":8901151498,"osm_tipo":"node","tipo_lugar":"suburb"},"geometry":{"type":"Point","coordinates":[-51.0858005,-29.565939]}}]}