{"type":"FeatureCollection","features":[{"type":"Feature","properties":{"nome":"Magalhães","osm_id":2391727589,"osm_tipo":"node","tipo_lugar":"suburb"},"geometry":{"type":"Point","coordinates":[-43.008067,-18.30841]}},{"type":"Feature","properties":{"nome":"Ponte","osm_id":10189230185,"osm_tipo":"node","tipo_lugar":"suburb"},"geometry":{"type":"Point","coordinates":[-43.0031172,-18.2894516]}},{"type":"Feature","properties":{"nome":"Chapadinha","osm_id":10191086446,"osm_tipo":"node","tipo_lugar":"suburb"},"geometry":{"type":"Point","coordinates":[-43.0109662,-18.2995027]}},{"type":"Feature","properties":{"nome":"Centro","osm_id":10191086447,"osm_tipo":"node","tipo_lugar":"suburb"},"geometry":{"type":"Point","coordinates":[-43.0076885,-18.2937831]}},{"type":"Feature","properties":{"nome":"Alto do Rosário","osm_id":10191086448,"osm_tipo":"node","tipo_lugar":"suburb"},"geometry":{"type":"Point","coordinates":[-43.0126345,-18.2937881]}}]}